{"GYM MODO BESTIA \ud83d\udcaa\ud83c\udffb": {"rank": "1", "playlistname": "GYM MODO BESTIA \ud83d\udcaa\ud83c\udffb", "noofsongs": "Street Therapy", "curator": "Brave Records", "listeners": "9,129", "streams": "11,603", "date": "Aug 3, 2021", "revenue": 69.62}, "Unknown83": {"rank": "2", "playlistname": "Unknown", "noofsongs": "3 songs", "curator": "chris.simpson99", "listeners": "2,760", "streams": "4,506", "date": "Oct 16, 2021", "revenue": 27.04}, "Chill rap vibes": {"rank": "3", "playlistname": "Chill rap vibes", "noofsongs": "Do It Right", "curator": "Masked Mortal Music", "listeners": "977", "streams": "1,252", "date": "Jan 31, 2022", "revenue": 7.51}, "Ami Rap 2022\ud83e\udd76\ud83d\udd25": {"rank": "4", "playlistname": "Ami Rap 2022\ud83e\udd76\ud83d\udd25", "noofsongs": "5 songs", "curator": "IG: nilss.hsm", "listeners": "289", "streams": "641", "date": "Sep 30, 2021", "revenue": 3.85}, "NLE Choppa - Beat Box \u201cFirst Day Out\u201d": {"rank": "5", "playlistname": "NLE Choppa - Beat Box \u201cFirst Day Out\u201d", "noofsongs": "6 songs", "curator": "Aaron", "listeners": "228", "streams": "586", "date": "Jul 9, 2021", "revenue": 3.52}, "No Billboards - Rap & Hip Hop Playlist 2022": {"rank": "6", "playlistname": "No Billboards - Rap & Hip Hop Playlist 2022", "noofsongs": "Do It Right", "curator": "No Billboards", "listeners": "374", "streams": "468", "date": "Dec 15, 2021", "revenue": 2.81}, "Unknown81": {"rank": "7", "playlistname": "Unknown", "noofsongs": "4 songs", "curator": "FionnMc2003", "listeners": "190", "streams": "468", "date": "Sep 12, 2021", "revenue": 2.81}, "Grind Time ": {"rank": "8", "playlistname": "Grind Time ", "noofsongs": "Street Therapy", "curator": "Bailey Walsh", "listeners": "332", "streams": "405", "date": "Oct 10, 2021", "revenue": 2.43}, "TRAP YANKEE \ud83c\uddfa\ud83c\uddf8": {"rank": "9", "playlistname": "TRAP YANKEE \ud83c\uddfa\ud83c\uddf8", "noofsongs": "Do It Right", "curator": "Facu Murillo", "listeners": "312", "streams": "388", "date": "Feb 18, 2022", "revenue": 2.33}, "BEST OF JUICE WRLD \ud83c\udf0e\ud83d\udd4a": {"rank": "10", "playlistname": "BEST OF JUICE WRLD \ud83c\udf0e\ud83d\udd4a", "noofsongs": "Do It Right", "curator": "Hiphop Heaven", "listeners": "261", "streams": "294", "date": "Feb 21, 2022", "revenue": 1.76}, "RAP MOTIVATION \ud83d\udcaa\ud83c\udffc2022 \ud83d\udd25": {"rank": "11", "playlistname": "RAP MOTIVATION \ud83d\udcaa\ud83c\udffc2022 \ud83d\udd25", "noofsongs": "Do It Right", "curator": "Riki Playlister", "listeners": "221", "streams": "266", "date": "Dec 8, 2021", "revenue": 1.6}, "VANO 3000 [adult swim]": {"rank": "12", "playlistname": "VANO 3000 [adult swim]", "noofsongs": "Goldie", "curator": "sarah smorholm", "listeners": "170", "streams": "240", "date": "Oct 15, 2021", "revenue": 1.44}, "Chill Hip Hop - Rap & Hip Hop Music 2021 ": {"rank": "13", "playlistname": "Chill Hip Hop - Rap & Hip Hop Music 2021 ", "noofsongs": "2 songs", "curator": "Filet Flows", "listeners": "143", "streams": "234", "date": "Jul 29, 2021", "revenue": 1.4}, "Filet Flows Rap Playlist 2022": {"rank": "14", "playlistname": "Filet Flows Rap Playlist 2022", "noofsongs": "Do It Right", "curator": "Cody Lucero", "listeners": "187", "streams": "221", "date": "Dec 15, 2021", "revenue": 1.33}, "Demon Mode \ud83d\ude80\ud83d\ude80": {"rank": "15", "playlistname": "Demon Mode \ud83d\ude80\ud83d\ude80", "noofsongs": "Street Therapy", "curator": "Nethmin", "listeners": "178", "streams": "216", "date": "Dec 19, 2021", "revenue": 1.3}, "Weekend Mood": {"rank": "16", "playlistname": "Weekend Mood", "noofsongs": "Do It Right", "curator": "moods.network", "listeners": "178", "streams": "194", "date": "Feb 18, 2022", "revenue": 1.16}, "\ud83d\udd25\ud83c\udfc0HYPE Basket warmup list": {"rank": "17", "playlistname": "\ud83d\udd25\ud83c\udfc0HYPE Basket warmup list", "noofsongs": "4 songs", "curator": "Nikolaj Klinge", "listeners": "82", "streams": "173", "date": "Jul 12, 2021", "revenue": 1.04}, "Rap Tune": {"rank": "18", "playlistname": "Rap Tune", "noofsongs": "2 songs", "curator": "Bryan Scott", "listeners": "75", "streams": "157", "date": "Jan 8, 2022", "revenue": 0.94}, "WEED PLAYLIST 2022": {"rank": "19", "playlistname": "WEED PLAYLIST 2022", "noofsongs": "2 songs", "curator": "Hype ur Track", "listeners": "126", "streams": "155", "date": "Sep 20, 2021", "revenue": 0.93}, "Smoking Weed Music": {"rank": "20", "playlistname": "Smoking Weed Music", "noofsongs": "2 songs", "curator": "Cece", "listeners": "60", "streams": "106", "date": "Nov 6, 2021", "revenue": 0.64}, "Sexy Beats": {"rank": "21", "playlistname": "Sexy Beats", "noofsongs": "Street Therapy", "curator": "Jordan Walt", "listeners": "63", "streams": "100", "date": "Dec 6, 2021", "revenue": 0.6}, "Chill rap vibes 2022": {"rank": "22", "playlistname": "Chill rap vibes 2022", "noofsongs": "Goldie", "curator": "Hiphoplists", "listeners": "82", "streams": "94", "date": "Sep 25, 2021", "revenue": 0.56}, "Came From Nothin": {"rank": "23", "playlistname": "Came From Nothin", "noofsongs": "Goldie", "curator": "Don\u2019t Regret This", "listeners": "86", "streams": "90", "date": "Oct 28, 2021", "revenue": 0.54}, "Astronaut In The Ocean\ud83d\udd25": {"rank": "24", "playlistname": "Astronaut In The Ocean\ud83d\udd25", "noofsongs": "Goldie", "curator": "Frank Strudahl Hansen", "listeners": "57", "streams": "82", "date": "Sep 29, 2021", "revenue": 0.49}, "Canciones para dormir": {"rank": "25", "playlistname": "Canciones para dormir", "noofsongs": "Goldie", "curator": "Francisco Ruiz", "listeners": "65", "streams": "79", "date": "Oct 12, 2021", "revenue": 0.47}, "Trap Music 2022 \ud83d\ude08\ud83d\udd25\ud83d\udcaf": {"rank": "26", "playlistname": "Trap Music 2022 \ud83d\ude08\ud83d\udd25\ud83d\udcaf", "noofsongs": "Do It Right", "curator": "Legendary Super Saiyan Broly:)", "listeners": "76", "streams": "78", "date": "Feb 21, 2022", "revenue": 0.47}, "Sad Vibes ": {"rank": "27", "playlistname": "Sad Vibes ", "noofsongs": "Goldie", "curator": "XINCLAIR", "listeners": "70", "streams": "75", "date": "Feb 21, 2022", "revenue": 0.45}, "Dirty Songs \ud83d\ude0f\ud83d\ude08\ud83d\udc8b": {"rank": "28", "playlistname": "Dirty Songs \ud83d\ude0f\ud83d\ude08\ud83d\udc8b", "noofsongs": "Do It Right", "curator": "Kt's WRLD \ud83e\udd8b\ud83c\udf0e\ud83e\udd74", "listeners": "70", "streams": "71", "date": "Feb 21, 2022", "revenue": 0.43}, "Music for weed lovers": {"rank": "29", "playlistname": "Music for weed lovers", "noofsongs": "2 songs", "curator": "music lover", "listeners": "24", "streams": "66", "date": "Sep 15, 2021", "revenue": 0.4}, "Bad Gurl": {"rank": "30", "playlistname": "Bad Gurl", "noofsongs": "Street Therapy", "curator": "Black is New Color", "listeners": "64", "streams": "64", "date": "Oct 28, 2021", "revenue": 0.38}, "SAMURAI CHAMPLOO ": {"rank": "31", "playlistname": "SAMURAI CHAMPLOO ", "noofsongs": "2 songs", "curator": "Phyllis Chen", "listeners": "52", "streams": "63", "date": "Dec 17, 2021", "revenue": 0.38}, "Chillout Hip Hop / Smooth Rap": {"rank": "32", "playlistname": "Chillout Hip Hop / Smooth Rap", "noofsongs": "Goldie", "curator": "Marco Pizarro", "listeners": "48", "streams": "56", "date": "Jun 3, 2021", "revenue": 0.34}, "tik tok songs that are actually good": {"rank": "33", "playlistname": "tik tok songs that are actually good", "noofsongs": "Do It Right", "curator": "lana lopez", "listeners": "45", "streams": "54", "date": "Feb 18, 2022", "revenue": 0.32}, "Sad Face ": {"rank": "34", "playlistname": "Sad Face ", "noofsongs": "Goldie", "curator": "XINCLAIR", "listeners": "51", "streams": "53", "date": "Feb 21, 2022", "revenue": 0.32}, "GYM HYPE": {"rank": "35", "playlistname": "GYM HYPE", "noofsongs": "Street Therapy", "curator": "Bailey Walsh", "listeners": "41", "streams": "52", "date": "Oct 10, 2021", "revenue": 0.31}, "Tiktok Global Hits \u2022 Bong Bing Cristale \u2022 Yonce Remix LV \u2022 Keep On Rollin King G\u2022 Love Game Gimme Mo": {"rank": "36", "playlistname": "Tiktok Global Hits \u2022 Bong Bing Cristale \u2022 Yonce Remix LV \u2022 Keep On Rollin King G\u2022 Love Game Gimme Mo", "noofsongs": "Goldie", "curator": "AfrobeatsGlobalPlaylists", "listeners": "37", "streams": "41", "date": "Jun 11, 2021", "revenue": 0.25}, "Tik tok slowed+reverb\ud83c\udfb6\ud83d\udc8b": {"rank": "37", "playlistname": "Tik tok slowed+reverb\ud83c\udfb6\ud83d\udc8b", "noofsongs": "Street Therapy", "curator": "Harshika\u2728", "listeners": "36", "streams": "41", "date": "Oct 3, 2021", "revenue": 0.25}, "SHEESH \ud83d\udcaf\ud83e\udd18\ud83c\udffc": {"rank": "38", "playlistname": "SHEESH \ud83d\udcaf\ud83e\udd18\ud83c\udffc", "noofsongs": "Street Therapy", "curator": "Pascal Su", "listeners": "33", "streams": "38", "date": "Jul 23, 2021", "revenue": 0.23}, "Chicago Drill": {"rank": "39", "playlistname": "Chicago Drill", "noofsongs": "Do It Right", "curator": "carteralv", "listeners": "37", "streams": "37", "date": "Feb 21, 2022", "revenue": 0.22}, "GYM Modo Bestia 2022\ud83d\udcaa\ud83c\udffb": {"rank": "40", "playlistname": "GYM Modo Bestia 2022\ud83d\udcaa\ud83c\udffb", "noofsongs": "Street Therapy", "curator": "DMONOID", "listeners": "31", "streams": "35", "date": "Oct 19, 2021", "revenue": 0.21}, "The Playlist of Greek Gods": {"rank": "41", "playlistname": "The Playlist of Greek Gods", "noofsongs": "2 songs", "curator": "Aidan M", "listeners": "24", "streams": "34", "date": "Sep 5, 2021", "revenue": 0.2}, "Chilliger Amirap\ud83c\udf41": {"rank": "42", "playlistname": "Chilliger Amirap\ud83c\udf41", "noofsongs": "5 songs", "curator": "Lukas Arnold", "listeners": "25", "streams": "32", "date": "Nov 1, 2021", "revenue": 0.19}, "foolin around yvngxchris (unreleased)": {"rank": "43", "playlistname": "foolin around yvngxchris (unreleased)", "noofsongs": "Do It Right", "curator": "@codymgmt", "listeners": "18", "streams": "32", "date": "Feb 21, 2022", "revenue": 0.19}, "tiktok songs slowed 2022": {"rank": "44", "playlistname": "tiktok songs slowed 2022", "noofsongs": "Street Therapy", "curator": "SoundWave", "listeners": "21", "streams": "30", "date": "Sep 22, 2021", "revenue": 0.18}, "f*ck me like you want me": {"rank": "45", "playlistname": "f*ck me like you want me", "noofsongs": "Do It Right", "curator": "@codymgmt", "listeners": "22", "streams": "26", "date": "Feb 21, 2022", "revenue": 0.16}, "Fortnite Highlights 2021": {"rank": "46", "playlistname": "Fortnite Highlights 2021", "noofsongs": "Street Therapy", "curator": "KryyX", "listeners": "23", "streams": "25", "date": "Oct 5, 2021", "revenue": 0.15}, "Dark Night ": {"rank": "47", "playlistname": "Dark Night ", "noofsongs": "Goldie", "curator": "Diego Carballo", "listeners": "23", "streams": "24", "date": "Jan 19, 2022", "revenue": 0.14}, "Bad bitch playlist\ud83d\udc95": {"rank": "48", "playlistname": "Bad bitch playlist\ud83d\udc95", "noofsongs": "Goldie", "curator": "Emma B\u00f8rslien", "listeners": "19", "streams": "24", "date": "Jul 14, 2021", "revenue": 0.14}, "Unknown3": {"rank": "49", "playlistname": "Unknown", "noofsongs": "Goldie", "curator": "clara siberg", "listeners": "15", "streams": "22", "date": "Oct 29, 2021", "revenue": 0.13}, "tiktok february 2022": {"rank": "50", "playlistname": "tiktok february 2022", "noofsongs": "Street Therapy", "curator": "clauloopezz", "listeners": "20", "streams": "21", "date": "Oct 1, 2021", "revenue": 0.13}, "Brassica 2022 Official Playlist": {"rank": "51", "playlistname": "Brassica 2022 Official Playlist", "noofsongs": "Do It Right", "curator": "brassicaadmin", "listeners": "4", "streams": "18", "date": "Jan 9, 2022", "revenue": 0.11}, "Boom Bap & Wu-Tang & Chill Hop": {"rank": "52", "playlistname": "Boom Bap & Wu-Tang & Chill Hop", "noofsongs": "Goldie", "curator": "Larry Hip-Hop Head", "listeners": "9", "streams": "17", "date": "May 13, 2021", "revenue": 0.1}, "RUNNING RAP 2022 \ud83e\udd47": {"rank": "53", "playlistname": "RUNNING RAP 2022 \ud83e\udd47", "noofsongs": "2 songs", "curator": "Guillermo Prudenciano Martin", "listeners": "11", "streams": "15", "date": "Jun 2, 2021", "revenue": 0.09}, "V I B E S \ud83d\udca8": {"rank": "54", "playlistname": "V I B E S \ud83d\udca8", "noofsongs": "Goldie", "curator": "Axel Anakin Abela", "listeners": "9", "streams": "13", "date": "Jul 11, 2021", "revenue": 0.08}, "I got a lil olda, my heart got colder\ud83d\udc94": {"rank": "55", "playlistname": "I got a lil olda, my heart got colder\ud83d\udc94", "noofsongs": "Do It Right", "curator": "@codymgmt", "listeners": "11", "streams": "12", "date": "Feb 21, 2022", "revenue": 0.07}, "disrespectful / demon time": {"rank": "56", "playlistname": "disrespectful / demon time", "noofsongs": "Street Therapy", "curator": "Lukas Lainsalu", "listeners": "10", "streams": "12", "date": "Aug 12, 2021", "revenue": 0.07}, "Rap Vibes 2022 \ud83d\udca4": {"rank": "57", "playlistname": "Rap Vibes 2022 \ud83d\udca4", "noofsongs": "Basquiat (Interlude)", "curator": "Zzz", "listeners": "8", "streams": "12", "date": "Jun 13, 2021", "revenue": 0.07}, "Gaming Trap & Rap | Gaming Music 2021 | ": {"rank": "58", "playlistname": "Gaming Trap & Rap | Gaming Music 2021 | ", "noofsongs": "Street Therapy", "curator": "Apg.music", "listeners": "9", "streams": "11", "date": "Jun 21, 2021", "revenue": 0.07}, "FUCK SHIT HARD RAW DISTORTED YELLING SCREAMING MEME TIKTOK NEW TRAP MUSIC \ud83d\ude21": {"rank": "59", "playlistname": "FUCK SHIT HARD RAW DISTORTED YELLING SCREAMING MEME TIKTOK NEW TRAP MUSIC \ud83d\ude21", "noofsongs": "Do It Right", "curator": "OHSAMMY\ud83d\ude0d\ud83d\ude0d", "listeners": "10", "streams": "10", "date": "\u2014", "revenue": 0.06}, "Big Bootie Mix Vol. 18 ~ Two Friends": {"rank": "60", "playlistname": "Big Bootie Mix Vol. 18 ~ Two Friends", "noofsongs": "Street Therapy", "curator": "ispytunes", "listeners": "9", "streams": "10", "date": "Jul 22, 2021", "revenue": 0.06}, "HYPED": {"rank": "61", "playlistname": "HYPED", "noofsongs": "2 songs", "curator": "ambertakara", "listeners": "9", "streams": "9", "date": "Jun 23, 2021", "revenue": 0.05}, "low vibe rap": {"rank": "62", "playlistname": "low vibe rap", "noofsongs": "Goldie", "curator": "freshgoodies", "listeners": "9", "streams": "9", "date": "Feb 21, 2022", "revenue": 0.05}, "Rap English - Hip Hop 90s & 2000": {"rank": "63", "playlistname": "Rap English - Hip Hop 90s & 2000", "noofsongs": "Do It Right", "curator": "Coweer_Playlist", "listeners": "9", "streams": "9", "date": "Jan 27, 2022", "revenue": 0.05}, "HIP HOP WORKOUT \ud83c\udfcb\ufe0f": {"rank": "64", "playlistname": "HIP HOP WORKOUT \ud83c\udfcb\ufe0f", "noofsongs": "3 songs", "curator": "Riki Playlister", "listeners": "5", "streams": "9", "date": "May 25, 2021", "revenue": 0.05}, "hip hopzinho 00s": {"rank": "65", "playlistname": "hip hopzinho 00s", "noofsongs": "Goldie", "curator": "N\u00c3O TENHO ROUPA", "listeners": "8", "streams": "8", "date": "Aug 26, 2021", "revenue": 0.05}, "Clean Rap Caviar": {"rank": "66", "playlistname": "Clean Rap Caviar", "noofsongs": "Do It Right", "curator": "1210608982", "listeners": "5", "streams": "8", "date": "Dec 8, 2021", "revenue": 0.05}, "POV: You Passed Me The Aux (V.1)": {"rank": "67", "playlistname": "POV: You Passed Me The Aux (V.1)", "noofsongs": "Street Therapy", "curator": "WhoIsTK? (@kingtkmusic)", "listeners": "6", "streams": "6", "date": "Jul 13, 2021", "revenue": 0.04}, "MVP-WBF": {"rank": "68", "playlistname": "MVP-WBF", "noofsongs": "Do It Right", "curator": "hyricle", "listeners": "2", "streams": "6", "date": "Jan 30, 2022", "revenue": 0.04}, "HipHop & RnB 2021 Vibes": {"rank": "69", "playlistname": "HipHop & RnB 2021 Vibes", "noofsongs": "Goldie", "curator": "Nicky Larson", "listeners": "2", "streams": "6", "date": "Dec 8, 2021", "revenue": 0.04}, "Trap Hit | Rap Hits \u26a1": {"rank": "91", "playlistname": "Trap Hit | Rap Hits \u26a1", "noofsongs": "Street Therapy", "curator": "oceanify", "listeners": "3", "streams": "3", "date": "Jun 10, 2021", "revenue": 0.02}, "Dangerously In Love (772 Love Pt. 2) \u2013 YNW Melly": {"rank": "71", "playlistname": "Dangerously In Love (772 Love Pt. 2) \u2013 YNW Melly", "noofsongs": "Do It Right", "curator": "\ud835\udd93\ud835\udd8e\ud835\udd96", "listeners": "5", "streams": "5", "date": "Feb 22, 2022", "revenue": 0.03}, "Gym ": {"rank": "72", "playlistname": "Gym ", "noofsongs": "Street Therapy", "curator": "Jenny Luav", "listeners": "5", "streams": "5", "date": "Dec 6, 2021", "revenue": 0.03}, "New Music: Rap, Hip-Hop, Trap, Pop": {"rank": "73", "playlistname": "New Music: Rap, Hip-Hop, Trap, Pop", "noofsongs": "Street Therapy", "curator": "T", "listeners": "5", "streams": "5", "date": "Jul 19, 2021", "revenue": 0.03}, "dracoo ": {"rank": "74", "playlistname": "dracoo ", "noofsongs": "Goldie", "curator": "Char.low", "listeners": "2", "streams": "5", "date": "Dec 10, 2021", "revenue": 0.03}, "PJ GYM": {"rank": "75", "playlistname": "PJ GYM", "noofsongs": "Street Therapy", "curator": "Jess", "listeners": "2", "streams": "5", "date": "Jan 30, 2022", "revenue": 0.03}, "ip op": {"rank": "76", "playlistname": "ip op", "noofsongs": "Do It Right", "curator": "Sonny Hope", "listeners": "2", "streams": "5", "date": "Jan 3, 2022", "revenue": 0.03}, "\u25cf\u25cb": {"rank": "77", "playlistname": "\u25cf\u25cb", "noofsongs": "Street Therapy", "curator": "Alan Parada", "listeners": "2", "streams": "5", "date": "Jan 27, 2022", "revenue": 0.03}, "Old School RnB, 90s, 2000s R&B": {"rank": "78", "playlistname": "Old School RnB, 90s, 2000s R&B", "noofsongs": "Goldie", "curator": "karolrodis", "listeners": "2", "streams": "5", "date": "\u2014", "revenue": 0.03}, "minecraft": {"rank": "79", "playlistname": "minecraft", "noofsongs": "Do It Right", "curator": "sarah smorholm", "listeners": "4", "streams": "4", "date": "Dec 11, 2021", "revenue": 0.02}, "Hits Hop \ud83d\udd25": {"rank": "80", "playlistname": "Hits Hop \ud83d\udd25", "noofsongs": "Street Therapy", "curator": "Thastreams", "listeners": "4", "streams": "4", "date": "Jun 13, 2021", "revenue": 0.02}, "7220 - Lil Durk (ALBUM)": {"rank": "81", "playlistname": "7220 - Lil Durk (ALBUM)", "noofsongs": "Do It Right", "curator": "@RayRadio_", "listeners": "4", "streams": "4", "date": "Feb 15, 2022", "revenue": 0.02}, "Night Check - Underground Hip Hop": {"rank": "82", "playlistname": "Night Check - Underground Hip Hop", "noofsongs": "Real is Back", "curator": "Vlad Dobrescu", "listeners": "3", "streams": "4", "date": "Jan 17, 2021", "revenue": 0.02}, "Maryann \u2764\ufe0f\u200d\ud83e\ude79": {"rank": "83", "playlistname": "Maryann \u2764\ufe0f\u200d\ud83e\ude79", "noofsongs": "Do It Right", "curator": "Mary<3", "listeners": "2", "streams": "4", "date": "Dec 25, 2021", "revenue": 0.02}, "\ud83c\udfa4\u270c\ufe0f": {"rank": "84", "playlistname": "\ud83c\udfa4\u270c\ufe0f", "noofsongs": "Song title not available", "curator": "Luca Zapata", "listeners": "2", "streams": "4", "date": "Jan 9, 2022", "revenue": 0.02}, "\ud83d\udcaa\ud83c\udffb/Gym Beast/\ud83d\ude08": {"rank": "85", "playlistname": "\ud83d\udcaa\ud83c\udffb/Gym Beast/\ud83d\ude08", "noofsongs": "Street Therapy", "curator": "Aar\u00f3n", "listeners": "2", "streams": "4", "date": "Feb 8, 2022", "revenue": 0.02}, "ThisBe2Good": {"rank": "86", "playlistname": "ThisBe2Good", "noofsongs": "Goldie", "curator": "Rowan Gowdy", "listeners": "2", "streams": "4", "date": "Feb 14, 2022", "revenue": 0.02}, "Lift P": {"rank": "87", "playlistname": "Lift P", "noofsongs": "What Can You Say", "curator": "cayton.lund", "listeners": "2", "streams": "4", "date": "Sep 30, 2021", "revenue": 0.02}, "Rap Hits | Trap Trends 2021 \u26a1 | Hip Hop Hits": {"rank": "88", "playlistname": "Rap Hits | Trap Trends 2021 \u26a1 | Hip Hop Hits", "noofsongs": "Street Therapy", "curator": "Other Way Around", "listeners": "3", "streams": "3", "date": "Jun 13, 2021", "revenue": 0.02}, "work": {"rank": "89", "playlistname": "work", "noofsongs": "Goldie", "curator": "liamjacquesboyle", "listeners": "3", "streams": "3", "date": "Jul 26, 2021", "revenue": 0.02}, "Savage Trap \u26a1": {"rank": "90", "playlistname": "Savage Trap \u26a1", "noofsongs": "Street Therapy", "curator": "Emotive Sounds", "listeners": "3", "streams": "3", "date": "Jun 10, 2021", "revenue": 0.02}, "Unknown4": {"rank": "92", "playlistname": "Unknown", "noofsongs": "Song title not available", "curator": "\ud83d\udda4Mia\ud83d\udd25", "listeners": "3", "streams": "3", "date": "Nov 6, 2021", "revenue": 0.02}, "DEFJAM AND FRIENDS - OLD BUT GOLD - TIKTOK": {"rank": "93", "playlistname": "DEFJAM AND FRIENDS - OLD BUT GOLD - TIKTOK", "noofsongs": "Goldie", "curator": "Adem DefJam", "listeners": "3", "streams": "3", "date": "Dec 14, 2021", "revenue": 0.02}, "i'll drive ": {"rank": "94", "playlistname": "i'll drive ", "noofsongs": "Do It Right", "curator": "Jack", "listeners": "3", "streams": "3", "date": "Jan 2, 2022", "revenue": 0.02}, "GYM LEG DAY": {"rank": "95", "playlistname": "GYM LEG DAY", "noofsongs": "Song title not available", "curator": "Ximena Soto", "listeners": "3", "streams": "3", "date": "Dec 14, 2021", "revenue": 0.02}, "Chill": {"rank": "96", "playlistname": "Chill", "noofsongs": "Goldie", "curator": "Jackson Gray", "listeners": "2", "streams": "3", "date": "Oct 1, 2021", "revenue": 0.02}, "Feel IT": {"rank": "97", "playlistname": "Feel IT", "noofsongs": "Street Therapy", "curator": "JustSad", "listeners": "2", "streams": "3", "date": "Jan 14, 2022", "revenue": 0.02}, "Rap for chilling": {"rank": "98", "playlistname": "Rap for chilling", "noofsongs": "Goldie", "curator": "Jules", "listeners": "2", "streams": "3", "date": "May 29, 2021", "revenue": 0.02}, "Certified": {"rank": "99", "playlistname": "Certified", "noofsongs": "Do It Right", "curator": "Cgarmit", "listeners": "2", "streams": "3", "date": "Dec 20, 2021", "revenue": 0.02}, "Smoke list \ud83c\udf41": {"rank": "100", "playlistname": "Smoke list \ud83c\udf41", "noofsongs": "Goldie", "curator": "Niamh22xoxo", "listeners": "2", "streams": "3", "date": "Jul 18, 2021", "revenue": 0.02}}